LICENCE.txt
MANIFEST.in
README.md
setup.cfg
setup.py
TOPSIS_Lakshya_101803492/__init__.py
TOPSIS_Lakshya_101803492.egg-info/PKG-INFO
TOPSIS_Lakshya_101803492.egg-info/SOURCES.txt
TOPSIS_Lakshya_101803492.egg-info/dependency_links.txt
TOPSIS_Lakshya_101803492.egg-info/requires.txt
TOPSIS_Lakshya_101803492.egg-info/top_level.txt