Metadata-Version: 2.1
Name: TOPSIS-Lakshya-101803492
Version: 0.0.65
Summary: Implementation of Multiple Criteria Decision Making (MCDM) using TOPSIS in Python.
Home-page: https://github.com/lakkshh
Author: Lakshya Gupta
Author-email: lg0605@gmail.com
License: MIT
Download-URL: https://github.com/lakkshh/TOPSIS_Python/archive/0.0.2.tar.gz
Keywords: simple,topsis,implementation,python
Platform: UNKNOWN
Classifier: Development Status :: 5 - Production/Stable
Classifier: Intended Audience :: Education
Classifier: Operating System :: OS Independent
Classifier: License :: OSI Approved :: MIT License
Classifier: Programming Language :: Python :: 3
Requires-Python: >=3.0
